sink/__init__.py
sink/actions.py
sink/applications.py
sink/check.py
sink/command.py
sink/config.py
sink/db.py
sink/deploy.py
sink/init.py
sink/rsync.py
sink/sink.py
sink/ssh.py
sink/ui.py
sink_dev_tool-0.1.0.dist-info/LICENSE
sink_dev_tool-0.1.0.dist-info/METADATA
sink_dev_tool-0.1.0.dist-info/WHEEL
sink_dev_tool-0.1.0.dist-info/entry_points.txt
sink_dev_tool-0.1.0.dist-info/top_level.txt
sink_dev_tool-0.1.0.dist-info/RECORD
