Metadata-Version: 2.1
Name: sink-dev-tool
Version: 0.1.0
Summary: Sink is a command line tool that helps with common tasks for websites.
Home-page: https://github.com/8cylinder/sink
Author: UNKNOWN
Author-email: UNKNOWN
License: UNKNOWN
Platform: UNKNOWN
Requires-Dist: PyYAML
Requires-Dist: click
